LICENSE
batche/__init__.py
batche/batche.py
batche/lrucache.py
batche-0.1.1.dist-info/LICENSE
batche-0.1.1.dist-info/METADATA
batche-0.1.1.dist-info/WHEEL
batche-0.1.1.dist-info/RECORD
