Metadata-Version: 2.1
Name: batche
Version: 0.1.1
Summary: batch caching decorator
Home-page: https://github.com/gautierdag/batche
License: MIT
Author: Gautier Dagan
Author-email: gautier.dagan@ed.ac.uk
Requires-Python: >=3.8,<4.0
Classifier: License :: OSI Approved :: MIT License
Classifier: Programming Language :: Python :: 3
Classifier: Programming Language :: Python :: 3.8
Classifier: Programming Language :: Python :: 3.9
Classifier: Programming Language :: Python :: 3.10
Classifier: Programming Language :: Python :: 3.11
Project-URL: Repository, https://github.com/gautierdag/batche
